sbx_sbx2hf/__init__.py
sbx_sbx2hf/exporters.py
sparv_sbx_sbx2hf-0.1.1.dist-info/METADATA
sparv_sbx_sbx2hf-0.1.1.dist-info/WHEEL
sparv_sbx_sbx2hf-0.1.1.dist-info/entry_points.txt
sparv_sbx_sbx2hf-0.1.1.dist-info/licenses/LICENSE
sparv_sbx_sbx2hf-0.1.1.dist-info/RECORD
